AUTHORS
CHANGES.rst
LICENSE
MANIFEST.in
README.rst
TODO.md
debian8-dist.sh
setup.py
pyvorcv.egg-info/PKG-INFO
pyvorcv.egg-info/SOURCES.txt
pyvorcv.egg-info/dependency_links.txt
pyvorcv.egg-info/requires.txt
pyvorcv.egg-info/top_level.txt
scripts/vorcv-circle-detection-calibration
scripts/vorcv-demo
vorcv/__init__.py
vorcv/circle_detection.py